[
  {
    "connectionId": "conn_1767292847494_6f36r1gat",
    "connectionName": "My Postgres Database",
    "query": "SELECT * FROM information_schema.tables LIMIT 10",
    "executedAt": "2026-01-02T06:23:40.805Z",
    "executionTime": 11,
    "rowCount": 10,
    "success": true,
    "id": "history_1767335020806_6n7x20wpc"
  },
  {
    "connectionId": "conn_1767292847494_6f36r1gat",
    "connectionName": "My Postgres Database",
    "query": "SELECT * FROM public.countries LIMIT 100",
    "executedAt": "2026-01-02T06:23:48.014Z",
    "executionTime": 5,
    "rowCount": 5,
    "success": true,
    "id": "history_1767335028016_w2xbrcary"
  },
  {
    "connectionId": "conn_1767358132773_4q9xyimqd",
    "connectionName": "My Postgres Database",
    "query": "SELECT * FROM information_schema.tables LIMIT 10",
    "executedAt": "2026-01-02T12:49:08.838Z",
    "executionTime": 11,
    "rowCount": 10,
    "success": true,
    "userEmail": "ayush@flipkart.com",
    "orgId": "flipkart.com",
    "id": "history_1767358148839_eoznndj6s"
  },
  {
    "connectionId": "conn_1767358132773_4q9xyimqd",
    "connectionName": "My Postgres Database",
    "query": "SELECT * FROM information_schema.tables LIMIT 10",
    "executedAt": "2026-01-02T12:49:09.678Z",
    "executionTime": 5,
    "rowCount": 10,
    "success": true,
    "userEmail": "ayush@flipkart.com",
    "orgId": "flipkart.com",
    "id": "history_1767358149678_rd29pdddm"
  },
  {
    "connectionId": "conn_1767358132773_4q9xyimqd",
    "connectionName": "My Postgres Database",
    "query": "SELECT * FROM information_schema.tables LIMIT 10",
    "executedAt": "2026-01-02T12:49:10.409Z",
    "executionTime": 4,
    "rowCount": 10,
    "success": true,
    "userEmail": "ayush@flipkart.com",
    "orgId": "flipkart.com",
    "id": "history_1767358150409_b53i2ozif"
  },
  {
    "connectionId": "conn_1767358132773_4q9xyimqd",
    "connectionName": "My Postgres Database",
    "query": "SELECT * FROM information_schema.tables LIMIT 10",
    "executedAt": "2026-01-02T12:49:11.047Z",
    "executionTime": 4,
    "rowCount": 10,
    "success": true,
    "userEmail": "ayush@flipkart.com",
    "orgId": "flipkart.com",
    "id": "history_1767358151047_xianr6woh"
  },
  {
    "connectionId": "conn_1767358132773_4q9xyimqd",
    "connectionName": "My Postgres Database",
    "query": "EXPLAIN (ANALYZE, COSTS, VERBOSE, BUFFERS, FORMAT JSON) SELECT * FROM information_schema.tables LIMIT 10",
    "executedAt": "2026-01-02T12:49:11.548Z",
    "executionTime": 10,
    "rowCount": 0,
    "success": true,
    "userEmail": "ayush@flipkart.com",
    "orgId": "flipkart.com",
    "id": "history_1767358151548_6o3qvlsna"
  },
  {
    "connectionId": "conn_1767358132773_4q9xyimqd",
    "connectionName": "My Postgres Database",
    "query": "SELECT * FROM information_schema.tables LIMIT 10",
    "executedAt": "2026-01-02T12:49:13.913Z",
    "executionTime": 5,
    "rowCount": 10,
    "success": true,
    "userEmail": "ayush@flipkart.com",
    "orgId": "flipkart.com",
    "id": "history_1767358153913_l5rpkgzo7"
  },
  {
    "connectionId": "conn_1767358132773_4q9xyimqd",
    "connectionName": "My Postgres Database",
    "query": "SELECT * FROM information_schema.tables LIMIT 10",
    "executedAt": "2026-01-02T12:49:14.639Z",
    "executionTime": 5,
    "rowCount": 10,
    "success": true,
    "userEmail": "ayush@flipkart.com",
    "orgId": "flipkart.com",
    "id": "history_1767358154639_ofhkzm6yl"
  },
  {
    "connectionId": "conn_1767358132773_4q9xyimqd",
    "connectionName": "My Postgres Database",
    "query": "SELECT * FROM information_schema.tables LIMIT 10",
    "executedAt": "2026-01-02T12:49:15.052Z",
    "executionTime": 4,
    "rowCount": 10,
    "success": true,
    "userEmail": "ayush@flipkart.com",
    "orgId": "flipkart.com",
    "id": "history_1767358155052_asoiu7s74"
  },
  {
    "connectionId": "conn_1767358132773_4q9xyimqd",
    "connectionName": "My Postgres Database",
    "query": "SELECT * FROM information_schema.tables LIMIT 10",
    "executedAt": "2026-01-02T12:56:07.741Z",
    "executionTime": 165,
    "rowCount": 10,
    "success": true,
    "userEmail": "ayush@flipkart.com",
    "orgId": "flipkart.com",
    "id": "history_1767358567742_a6oebcn0h"
  },
  {
    "connectionId": "conn_1767358132773_4q9xyimqd",
    "connectionName": "My Postgres Database",
    "query": "CREATE TABLE departments (\r\n    dept_id SERIAL PRIMARY KEY,\r\n    dept_name VARCHAR(100) UNIQUE NOT NULL,\r\n    created_at TIMESTAMP DEFAULT CURRENT_TIMESTAMP\r\n)",
    "executedAt": "2026-01-02T12:56:59.419Z",
    "executionTime": 181,
    "rowCount": 0,
    "success": true,
    "userEmail": "ayush@flipkart.com",
    "orgId": "flipkart.com",
    "id": "history_1767358619419_1jes7fobp"
  },
  {
    "connectionId": "conn_1767358132773_4q9xyimqd",
    "connectionName": "My Postgres Database",
    "query": "CREATE TABLE employees (\r\n    emp_id SERIAL PRIMARY KEY,\r\n    first_name VARCHAR(50) NOT NULL,\r\n    last_name VARCHAR(50),\r\n    email VARCHAR(100) UNIQUE NOT NULL,\r\n    phone VARCHAR(20),\r\n    salary NUMERIC(10,2) CHECK (salary >= 0),\r\n    dept_id INT REFERENCES departments(dept_id),\r\n    is_active BOOLEAN DEFAULT TRUE,\r\n    created_at TIMESTAMP DEFAULT CURRENT_TIMESTAMP\r\n)",
    "executedAt": "2026-01-02T12:57:08.431Z",
    "executionTime": 79,
    "rowCount": 0,
    "success": true,
    "userEmail": "ayush@flipkart.com",
    "orgId": "flipkart.com",
    "id": "history_1767358628431_0jdhlibfp"
  },
  {
    "connectionId": "conn_1767358132773_4q9xyimqd",
    "connectionName": "My Postgres Database",
    "query": "CREATE TABLE employee_addresses (\r\n    address_id SERIAL PRIMARY KEY,\r\n    emp_id INT REFERENCES employees(emp_id) ON DELETE CASCADE,\r\n    address_line TEXT,\r\n    city VARCHAR(50),\r\n    state VARCHAR(50),\r\n    country VARCHAR(50),\r\n    pincode VARCHAR(10)\r\n)",
    "executedAt": "2026-01-02T12:57:16.604Z",
    "executionTime": 40,
    "rowCount": 0,
    "success": true,
    "userEmail": "ayush@flipkart.com",
    "orgId": "flipkart.com",
    "id": "history_1767358636604_wpf5y8thh"
  },
  {
    "connectionId": "conn_1767358132773_4q9xyimqd",
    "connectionName": "My Postgres Database",
    "query": "CREATE TABLE employee_audit (\r\n    audit_id SERIAL PRIMARY KEY,\r\n    emp_id INT,\r\n    action VARCHAR(20),\r\n    old_data JSONB,\r\n    new_data JSONB,\r\n    action_time TIMESTAMP DEFAULT CURRENT_TIMESTAMP\r\n)",
    "executedAt": "2026-01-02T12:57:21.419Z",
    "executionTime": 34,
    "rowCount": 0,
    "success": true,
    "userEmail": "ayush@flipkart.com",
    "orgId": "flipkart.com",
    "id": "history_1767358641419_0ex8iwz56"
  },
  {
    "connectionId": "conn_1767358132773_4q9xyimqd",
    "connectionName": "My Postgres Database",
    "query": "INSERT INTO departments (dept_name)\r\nVALUES\r\n('Engineering'),\r\n('HR'),\r\n('Finance'),\r\n('Operations')",
    "executedAt": "2026-01-02T12:58:01.928Z",
    "executionTime": 17,
    "rowCount": 4,
    "success": true,
    "userEmail": "ayush@flipkart.com",
    "orgId": "flipkart.com",
    "id": "history_1767358681928_5b50b348t"
  },
  {
    "connectionId": "conn_1767358132773_4q9xyimqd",
    "connectionName": "My Postgres Database",
    "query": "INSERT INTO employees (\r\n    first_name,\r\n    last_name,\r\n    email,\r\n    phone,\r\n    salary,\r\n    dept_id\r\n)\r\nVALUES\r\n('Ayush', 'Gupta', 'ayush@company.com', '9999999999', 75000, 1),\r\n('Rahul', 'Sharma', 'rahul@company.com', '8888888888', 55000, 2),\r\n('Neha', 'Verma', 'neha@company.com', '7777777777', 65000, 1),\r\n('Priya', 'Singh', 'priya@company.com', '6666666666', 60000, 3)",
    "executedAt": "2026-01-02T12:58:09.014Z",
    "executionTime": 379,
    "rowCount": 4,
    "success": true,
    "userEmail": "ayush@flipkart.com",
    "orgId": "flipkart.com",
    "id": "history_1767358689014_yu8msqbv8"
  },
  {
    "connectionId": "conn_1767358132773_4q9xyimqd",
    "connectionName": "My Postgres Database",
    "query": "INSERT INTO employee_addresses (\r\n    emp_id,\r\n    address_line,\r\n    city,\r\n    state,\r\n    country,\r\n    pincode\r\n)\r\nVALUES\r\n(1, 'Sector 62', 'Noida', 'UP', 'India', '201301'),\r\n(2, 'MG Road', 'Bengaluru', 'Karnataka', 'India', '560001'),\r\n(3, 'Andheri East', 'Mumbai', 'Maharashtra', 'India', '400069'),\r\n(4, 'Salt Lake', 'Kolkata', 'West Bengal', 'India', '700091')",
    "executedAt": "2026-01-02T12:58:16.003Z",
    "executionTime": 10,
    "rowCount": 4,
    "success": true,
    "userEmail": "ayush@flipkart.com",
    "orgId": "flipkart.com",
    "id": "history_1767358696003_mov2e8k99"
  },
  {
    "connectionId": "conn_1767358132773_4q9xyimqd",
    "connectionName": "My Postgres Database",
    "query": "INSERT INTO employee_audit (\r\n    emp_id,\r\n    action,\r\n    old_data,\r\n    new_data\r\n)\r\nVALUES (\r\n    1,\r\n    'MANUAL_TEST',\r\n    NULL,\r\n    '{\"salary\":75000,\"status\":\"active\"}'\r\n)",
    "executedAt": "2026-01-02T12:58:20.173Z",
    "executionTime": 16,
    "rowCount": 1,
    "success": true,
    "userEmail": "ayush@flipkart.com",
    "orgId": "flipkart.com",
    "id": "history_1767358700173_9ebc91ici"
  },
  {
    "connectionId": "conn_1767358132773_4q9xyimqd",
    "connectionName": "My Postgres Database",
    "query": "CREATE OR REPLACE PROCEDURE add_employee(\r\n    p_first_name VARCHAR,\r\n    p_last_name VARCHAR,\r\n    p_email VARCHAR,\r\n    p_phone VARCHAR,\r\n    p_salary NUMERIC,\r\n    p_dept_id INT\r\n)\r\nLANGUAGE plpgsql\r\nAS $$\r\nBEGIN\r\n    INSERT INTO employees (\r\n        first_name, last_name, email, phone, salary, dept_id\r\n    )\r\n    VALUES (\r\n        p_first_name, p_last_name, p_email, p_phone, p_salary, p_dept_id\r\n    )",
    "executedAt": "2026-01-02T12:58:46.282Z",
    "executionTime": 0,
    "rowCount": 0,
    "success": false,
    "error": "Query execution failed: unterminated dollar-quoted string at or near \"$$\r\nBEGIN\r\n    INSERT INTO employees (\r\n        first_name, last_name, email, phone, salary, dept_id\r\n    )\r\n    VALUES (\r\n        p_first_name, p_last_name, p_email, p_phone, p_salary, p_dept_id\r\n    )\"",
    "userEmail": "ayush@flipkart.com",
    "orgId": "flipkart.com",
    "id": "history_1767358726282_nxz119gz2"
  },
  {
    "connectionId": "conn_1767358132773_4q9xyimqd",
    "connectionName": "My Postgres Database",
    "query": "CREATE OR REPLACE PROCEDURE add_employee(\r\n    p_first_name VARCHAR,\r\n    p_last_name VARCHAR,\r\n    p_email VARCHAR,\r\n    p_phone VARCHAR,\r\n    p_salary NUMERIC,\r\n    p_dept_id INT\r\n)\r\nLANGUAGE plpgsql\r\nAS $$\r\nBEGIN\r\n    INSERT INTO employees (\r\n        first_name,\r\n        last_name,\r\n        email,\r\n        phone,\r\n        salary,\r\n        dept_id\r\n    )\r\n    VALUES (\r\n        p_first_name,\r\n        p_last_name,\r\n        p_email,\r\n        p_phone,\r\n        p_salary,\r\n        p_dept_id",
    "executedAt": "2026-01-02T12:59:06.303Z",
    "executionTime": 0,
    "rowCount": 0,
    "success": false,
    "error": "Query execution failed: unterminated dollar-quoted string at or near \"$$\r\nBEGIN\r\n    INSERT INTO employees (\r\n        first_name,\r\n        last_name,\r\n        email,\r\n        phone,\r\n        salary,\r\n        dept_id\r\n    )\r\n    VALUES (\r\n        p_first_name,\r\n        p_last_name,\r\n        p_email,\r\n        p_phone,\r\n        p_salary,\r\n        p_dept_id\"",
    "userEmail": "ayush@flipkart.com",
    "orgId": "flipkart.com",
    "id": "history_1767358746303_ydw4n39mo"
  },
  {
    "connectionId": "conn_1767358132773_4q9xyimqd",
    "connectionName": "My Postgres Database",
    "query": "CREATE OR REPLACE PROCEDURE add_employee(\r\n    p_first_name VARCHAR,\r\n    p_last_name VARCHAR,\r\n    p_email VARCHAR,\r\n    p_phone VARCHAR,\r\n    p_salary NUMERIC,\r\n    p_dept_id INT\r\n)\r\nLANGUAGE plpgsql\r\nAS $$\r\nBEGIN\r\n    INSERT INTO employees (\r\n        first_name,\r\n        last_name,\r\n        email,\r\n        phone,\r\n        salary,\r\n        dept_id\r\n    )\r\n    VALUES (\r\n        p_first_name,\r\n        p_last_name,\r\n        p_email,\r\n        p_phone,\r\n        p_salary,\r\n        p_dept_id",
    "executedAt": "2026-01-02T12:59:26.894Z",
    "executionTime": 0,
    "rowCount": 0,
    "success": false,
    "error": "Query execution failed: unterminated dollar-quoted string at or near \"$$\r\nBEGIN\r\n    INSERT INTO employees (\r\n        first_name,\r\n        last_name,\r\n        email,\r\n        phone,\r\n        salary,\r\n        dept_id\r\n    )\r\n    VALUES (\r\n        p_first_name,\r\n        p_last_name,\r\n        p_email,\r\n        p_phone,\r\n        p_salary,\r\n        p_dept_id\"",
    "userEmail": "ayush@flipkart.com",
    "orgId": "flipkart.com",
    "id": "history_1767358766894_xrejq6kgh"
  },
  {
    "connectionId": "conn_1767358132773_4q9xyimqd",
    "connectionName": "My Postgres Database",
    "query": "CREATE OR REPLACE PROCEDURE add_employee(\r\n    p_first_name VARCHAR,\r\n    p_last_name  VARCHAR,\r\n    p_email      VARCHAR,\r\n    p_phone      VARCHAR,\r\n    p_salary     NUMERIC,\r\n    p_dept_id    INT\r\n)\r\nLANGUAGE plpgsql\r\nAS\r\n$$\r\nBEGIN\r\n    INSERT INTO employees (\r\n        first_name,\r\n        last_name,\r\n        email,\r\n        phone,\r\n        salary,\r\n        dept_id\r\n    )\r\n    VALUES (\r\n        p_first_name,\r\n        p_last_name,\r\n        p_email,\r\n        p_phone,\r\n        p_salary,\r\n        p_dept_id\r\n    )",
    "executedAt": "2026-01-02T12:59:55.111Z",
    "executionTime": 0,
    "rowCount": 0,
    "success": false,
    "error": "Query execution failed: unterminated dollar-quoted string at or near \"$$\r\nBEGIN\r\n    INSERT INTO employees (\r\n        first_name,\r\n        last_name,\r\n        email,\r\n        phone,\r\n        salary,\r\n        dept_id\r\n    )\r\n    VALUES (\r\n        p_first_name,\r\n        p_last_name,\r\n        p_email,\r\n        p_phone,\r\n        p_salary,\r\n        p_dept_id\r\n    )\"",
    "userEmail": "ayush@flipkart.com",
    "orgId": "flipkart.com",
    "id": "history_1767358795111_59demyaa9"
  },
  {
    "connectionId": "conn_1767358132773_4q9xyimqd",
    "connectionName": "My Postgres Database",
    "query": "DO\r\n$$\r\nBEGIN\r\n    INSERT INTO employees (\r\n        first_name,\r\n        last_name,\r\n        email,\r\n        phone,\r\n        salary,\r\n        dept_id\r\n    )\r\n    VALUES (\r\n        'Ayush',\r\n        'Gupta',\r\n        'ayush@company.com',\r\n        '9999999999',\r\n        75000,\r\n        1\r\n    )",
    "executedAt": "2026-01-02T13:00:18.127Z",
    "executionTime": 0,
    "rowCount": 0,
    "success": false,
    "error": "Query execution failed: unterminated dollar-quoted string at or near \"$$\r\nBEGIN\r\n    INSERT INTO employees (\r\n        first_name,\r\n        last_name,\r\n        email,\r\n        phone,\r\n        salary,\r\n        dept_id\r\n    )\r\n    VALUES (\r\n        'Ayush',\r\n        'Gupta',\r\n        'ayush@company.com',\r\n        '9999999999',\r\n        75000,\r\n        1\r\n    )\"",
    "userEmail": "ayush@flipkart.com",
    "orgId": "flipkart.com",
    "id": "history_1767358818127_dlmrg92zd"
  },
  {
    "connectionId": "conn_1767358132773_4q9xyimqd",
    "connectionName": "My Postgres Database",
    "query": "INSERT INTO employees (\r\n    first_name,\r\n    last_name,\r\n    email,\r\n    phone,\r\n    salary,\r\n    dept_id\r\n)\r\nVALUES (\r\n    'Ayush',\r\n    'Gupta',\r\n    'ayush@company.com',\r\n    '9999999999',\r\n    75000,\r\n    1\r\n)",
    "executedAt": "2026-01-02T13:00:57.855Z",
    "executionTime": 0,
    "rowCount": 0,
    "success": false,
    "error": "Query execution failed: duplicate key value violates unique constraint \"employees_email_key\"",
    "userEmail": "ayush@flipkart.com",
    "orgId": "flipkart.com",
    "id": "history_1767358857855_qvpv4ydnv"
  },
  {
    "connectionId": "conn_1767358132773_4q9xyimqd",
    "connectionName": "My Postgres Database",
    "query": "DO\r\n$$\r\nBEGIN\r\n    INSERT INTO employees (first_name, last_name, email, phone, salary, dept_id)\r\n    VALUES ('Ayush', 'Gupta', 'ayush@company.com', '9999999999', 75000, 1)",
    "executedAt": "2026-01-02T13:01:06.416Z",
    "executionTime": 0,
    "rowCount": 0,
    "success": false,
    "error": "Query execution failed: unterminated dollar-quoted string at or near \"$$\r\nBEGIN\r\n    INSERT INTO employees (first_name, last_name, email, phone, salary, dept_id)\r\n    VALUES ('Ayush', 'Gupta', 'ayush@company.com', '9999999999', 75000, 1)\"",
    "userEmail": "ayush@flipkart.com",
    "orgId": "flipkart.com",
    "id": "history_1767358866416_yn53exm3f"
  },
  {
    "connectionId": "conn_1767358132773_4q9xyimqd",
    "connectionName": "My Postgres Database",
    "query": "CREATE OR REPLACE FUNCTION add_employee()\r\nRETURNS void\r\nLANGUAGE plpgsql\r\nAS $$\r\nBEGIN\r\n    INSERT INTO employees (first_name, last_name, email, phone, salary, dept_id)\r\n    VALUES ('Ayush', 'Gupta', 'ayush@company.com', '9999999999', 75000, 1)",
    "executedAt": "2026-01-02T13:01:14.660Z",
    "executionTime": 0,
    "rowCount": 0,
    "success": false,
    "error": "Query execution failed: unterminated dollar-quoted string at or near \"$$\r\nBEGIN\r\n    INSERT INTO employees (first_name, last_name, email, phone, salary, dept_id)\r\n    VALUES ('Ayush', 'Gupta', 'ayush@company.com', '9999999999', 75000, 1)\"",
    "userEmail": "ayush@flipkart.com",
    "orgId": "flipkart.com",
    "id": "history_1767358874660_i26xd0vm5"
  },
  {
    "connectionId": "conn_1767358132773_4q9xyimqd",
    "connectionName": "My Postgres Database",
    "query": "CREATE OR REPLACE FUNCTION add_employee()\r\nRETURNS void\r\nLANGUAGE plpgsql\r\nAS $$\r\nBEGIN\r\n    INSERT INTO employees (first_name, last_name, email, phone, salary, dept_id)\r\n    VALUES ('Ayush', 'Gupta', 'ayush@company.com', '9999999999', 75000, 1);\r\nEND;\r\n$$",
    "executedAt": "2026-01-02T13:12:07.651Z",
    "executionTime": 76,
    "rowCount": 0,
    "success": true,
    "userEmail": "ayush@flipkart.com",
    "orgId": "flipkart.com",
    "id": "history_1767359527652_ct2509lcd"
  },
  {
    "connectionId": "conn_1767358132773_4q9xyimqd",
    "connectionName": "My Postgres Database",
    "query": "-- Then call it:\r\nSELECT add_employee()",
    "executedAt": "2026-01-02T13:12:07.718Z",
    "executionTime": 0,
    "rowCount": 0,
    "success": false,
    "error": "Query execution failed: duplicate key value violates unique constraint \"employees_email_key\"",
    "userEmail": "ayush@flipkart.com",
    "orgId": "flipkart.com",
    "id": "history_1767359527718_6k888hmbp"
  },
  {
    "connectionId": "conn_1767358132773_4q9xyimqd",
    "connectionName": "My Postgres Database",
    "query": "CREATE OR REPLACE PROCEDURE add_employee(\r\n    p_first_name VARCHAR,\r\n    p_last_name  VARCHAR,\r\n    p_email      VARCHAR,\r\n    p_phone      VARCHAR,\r\n    p_salary     NUMERIC,\r\n    p_dept_id    INT\r\n)\r\nLANGUAGE plpgsql\r\nAS '\r\nBEGIN\r\n    INSERT INTO employees (\r\n        first_name, last_name, email, phone, salary, dept_id\r\n    )\r\n    VALUES (\r\n        p_first_name, p_last_name, p_email, p_phone, p_salary, p_dept_id\r\n    );\r\nEND;\r\n'",
    "executedAt": "2026-01-02T13:12:32.022Z",
    "executionTime": 12,
    "rowCount": 0,
    "success": true,
    "userEmail": "ayush@flipkart.com",
    "orgId": "flipkart.com",
    "id": "history_1767359552022_1oin2rez9"
  },
  {
    "connectionId": "conn_1767358132773_4q9xyimqd",
    "connectionName": "My Postgres Database",
    "query": "-- Call the procedure\r\nCALL add_employee(\r\n    'Rahul',\r\n    'Sharma', \r\n    'rahul@company.com',\r\n    '9876543210',\r\n    80000,\r\n    1\r\n)",
    "executedAt": "2026-01-02T13:13:17.454Z",
    "executionTime": 0,
    "rowCount": 0,
    "success": false,
    "error": "Query execution failed: duplicate key value violates unique constraint \"employees_email_key\"",
    "userEmail": "ayush@flipkart.com",
    "orgId": "flipkart.com",
    "id": "history_1767359597454_edck2r6wa"
  },
  {
    "connectionId": "conn_1767358132773_4q9xyimqd",
    "connectionName": "My Postgres Database",
    "query": "SELECT proname\r\nFROM pg_proc\r\nWHERE proname = 'add_employee'",
    "executedAt": "2026-01-02T13:17:54.108Z",
    "executionTime": 107,
    "rowCount": 2,
    "success": true,
    "userEmail": "ayush@flipkart.com",
    "orgId": "flipkart.com",
    "id": "history_1767359874108_u3d8wve24"
  },
  {
    "connectionId": "conn_1767358132773_4q9xyimqd",
    "connectionName": "My Postgres Database",
    "query": "SELECT proname\r\nFROM pg_proc\r\nWHERE proname = 'add_employee'",
    "executedAt": "2026-01-02T13:18:08.675Z",
    "executionTime": 6,
    "rowCount": 2,
    "success": true,
    "userEmail": "ayush@flipkart.com",
    "orgId": "flipkart.com",
    "id": "history_1767359888675_wizzckltc"
  },
  {
    "connectionId": "conn_1767358132773_4q9xyimqd",
    "connectionName": "My Postgres Database",
    "query": "CALL add_employee(\r\n    'Rahul',\r\n    'Sharma',\r\n    'rahul@company.com',\r\n    '9876543210',\r\n    80000,\r\n    1\r\n)",
    "executedAt": "2026-01-02T13:18:15.978Z",
    "executionTime": 0,
    "rowCount": 0,
    "success": false,
    "error": "Query execution failed: duplicate key value violates unique constraint \"employees_email_key\"",
    "userEmail": "ayush@flipkart.com",
    "orgId": "flipkart.com",
    "id": "history_1767359895978_byheqbj7b"
  },
  {
    "connectionId": "conn_1767358132773_4q9xyimqd",
    "connectionName": "My Postgres Database",
    "query": "CREATE OR REPLACE PROCEDURE add_employee(\r\n    p_first_name VARCHAR,\r\n    p_last_name  VARCHAR,\r\n    p_email      VARCHAR,\r\n    p_phone      VARCHAR,\r\n    p_salary     NUMERIC,\r\n    p_dept_id    INT\r\n)\r\nLANGUAGE plpgsql\r\nAS '\r\nBEGIN\r\n    INSERT INTO employees (\r\n        first_name,\r\n        last_name,\r\n        email,\r\n        phone,\r\n        salary,\r\n        dept_id\r\n    )\r\n    VALUES (\r\n        p_first_name,\r\n        p_last_name,\r\n        p_email,\r\n        p_phone,\r\n        p_salary,\r\n        p_dept_id\r\n    );\r\nEND;\r\n'",
    "executedAt": "2026-01-02T13:18:23.469Z",
    "executionTime": 26,
    "rowCount": 0,
    "success": true,
    "userEmail": "ayush@flipkart.com",
    "orgId": "flipkart.com",
    "id": "history_1767359903470_1vchzqees"
  },
  {
    "connectionId": "conn_1767358132773_4q9xyimqd",
    "connectionName": "My Postgres Database",
    "query": "CALL add_employee(\r\n    'Rahul',\r\n    'Sharma',\r\n    'rahul@company.com',\r\n    '9876543210',\r\n    80000,\r\n    1\r\n)",
    "executedAt": "2026-01-02T13:18:28.342Z",
    "executionTime": 0,
    "rowCount": 0,
    "success": false,
    "error": "Query execution failed: duplicate key value violates unique constraint \"employees_email_key\"",
    "userEmail": "ayush@flipkart.com",
    "orgId": "flipkart.com",
    "id": "history_1767359908342_24jxchbi6"
  },
  {
    "connectionId": "conn_1767358132773_4q9xyimqd",
    "connectionName": "My Postgres Database",
    "query": "CALL add_employee(\r\n    'Rahul',\r\n    'Sharma',\r\n    'rahul2@company.com',\r\n    '9876543210',\r\n    80000,\r\n    1\r\n)",
    "executedAt": "2026-01-02T13:18:59.847Z",
    "executionTime": 64,
    "rowCount": 0,
    "success": true,
    "userEmail": "ayush@flipkart.com",
    "orgId": "flipkart.com",
    "id": "history_1767359939848_leuwx77t5"
  },
  {
    "connectionId": "conn_1767358132773_4q9xyimqd",
    "connectionName": "My Postgres Database",
    "query": "CALL add_employee(\r\n    'Rahul',\r\n    'Sharma',\r\n    'rahul2@company.com',\r\n    '9876543210',\r\n    80000,\r\n    1\r\n)",
    "executedAt": "2026-01-02T13:20:06.732Z",
    "executionTime": 0,
    "rowCount": 0,
    "success": false,
    "error": "Query execution failed: duplicate key value violates unique constraint \"employees_email_key\"",
    "userEmail": "ayush@flipkart.com",
    "orgId": "flipkart.com",
    "id": "history_1767360006734_5likaiqc4"
  },
  {
    "connectionId": "conn_1767358132773_4q9xyimqd",
    "connectionName": "My Postgres Database",
    "query": "CALL add_employee(\r\n    'Rahul',\r\n    'Sharma',\r\n    'rahul2@company.com',\r\n    '9876543210',\r\n    80000,\r\n    1\r\n)",
    "executedAt": "2026-01-02T13:20:10.258Z",
    "executionTime": 0,
    "rowCount": 0,
    "success": false,
    "error": "Query execution failed: duplicate key value violates unique constraint \"employees_email_key\"",
    "userEmail": "ayush@flipkart.com",
    "orgId": "flipkart.com",
    "id": "history_1767360010258_abkb8bszd"
  },
  {
    "connectionId": "conn_1767358132773_4q9xyimqd",
    "connectionName": "My Postgres Database",
    "query": "SELECT\n    *\nFROM\n    information_schema.tables\nLIMIT\n    10",
    "executedAt": "2026-01-02T14:24:42.263Z",
    "executionTime": 17,
    "rowCount": 10,
    "success": true,
    "userEmail": "ayush@flipkart.com",
    "orgId": "flipkart.com",
    "id": "history_1767363882265_mrdia5cft"
  },
  {
    "connectionId": "conn_1767358132773_4q9xyimqd",
    "connectionName": "My Postgres Database",
    "query": "drop table employees",
    "executedAt": "2026-01-02T17:13:42.024Z",
    "executionTime": 0,
    "rowCount": 0,
    "success": false,
    "error": "Query execution failed: cannot drop table employees because other objects depend on it",
    "userEmail": "ayush@flipkart.com",
    "orgId": "flipkart.com",
    "id": "history_1767374022026_o8lfv5tpn"
  },
  {
    "connectionId": "conn_1767358132773_4q9xyimqd",
    "connectionName": "My Postgres Database",
    "query": "create table studentt",
    "executedAt": "2026-01-02T17:23:56.118Z",
    "executionTime": 0,
    "rowCount": 0,
    "success": false,
    "error": "Query execution failed: syntax error at end of input",
    "userEmail": "ayush@flipkart.com",
    "orgId": "flipkart.com",
    "id": "history_1767374636120_z50w5sd27"
  },
  {
    "connectionId": "conn_1767358132773_4q9xyimqd",
    "connectionName": "My Postgres Database",
    "query": "create table studentt",
    "executedAt": "2026-01-02T17:24:01.954Z",
    "executionTime": 0,
    "rowCount": 0,
    "success": false,
    "error": "Query execution failed: syntax error at end of input",
    "userEmail": "ayush@flipkart.com",
    "orgId": "flipkart.com",
    "id": "history_1767374641954_959iv5ewd"
  },
  {
    "connectionId": "conn_1767358132773_4q9xyimqd",
    "connectionName": "My Postgres Database",
    "query": "CREATE TABLE traveling_list_items (\r\n    id SERIAL PRIMARY KEY,\r\n    trip_name VARCHAR(100) NOT NULL,\r\n    item_name VARCHAR(100) NOT NULL,\r\n    category VARCHAR(50),\r\n    quantity INT DEFAULT 1,\r\n    is_packed BOOLEAN DEFAULT FALSE,\r\n    created_at TIMESTAMP DEFAULT CURRENT_TIMESTAMP\r\n)",
    "executedAt": "2026-01-02T17:24:51.857Z",
    "executionTime": 166,
    "rowCount": 0,
    "success": true,
    "userEmail": "ayush@flipkart.com",
    "orgId": "flipkart.com",
    "id": "history_1767374691857_dd7psag18"
  },
  {
    "connectionId": "conn_1767358132773_4q9xyimqd",
    "connectionName": "My Postgres Database",
    "query": "DROP TABLE IF EXISTS traveling_list_items",
    "executedAt": "2026-01-02T17:25:03.734Z",
    "executionTime": 56,
    "rowCount": 0,
    "success": true,
    "userEmail": "ayush@flipkart.com",
    "orgId": "flipkart.com",
    "id": "history_1767374703734_um537jtzr"
  },
  {
    "connectionId": "conn_1767358132773_4q9xyimqd",
    "connectionName": "My Postgres Database",
    "query": "CALL public.add_employee()",
    "executedAt": "2026-01-02T17:30:20.501Z",
    "executionTime": 0,
    "rowCount": 0,
    "success": false,
    "error": "Query execution failed: public.add_employee() is not a procedure",
    "userEmail": "ayush@flipkart.com",
    "orgId": "flipkart.com",
    "id": "history_1767375020504_r4uj10674"
  },
  {
    "connectionId": "conn_1767358132773_4q9xyimqd",
    "connectionName": "My Postgres Database",
    "query": "CREATE TABLE apples (\r\n    id SERIAL PRIMARY KEY,\r\n    variety TEXT,\r\n    quantity INT\r\n)",
    "executedAt": "2026-01-02T17:32:26.203Z",
    "executionTime": 296,
    "rowCount": 0,
    "success": true,
    "userEmail": "ayush@flipkart.com",
    "orgId": "flipkart.com",
    "id": "history_1767375146203_zxmtopzt7"
  },
  {
    "connectionId": "conn_1767358132773_4q9xyimqd",
    "connectionName": "My Postgres Database",
    "query": "INSERT INTO apples (variety, quantity) VALUES\r\n('Red', 10),\r\n('Green', 5),\r\n('Golden', 8)",
    "executedAt": "2026-01-02T17:32:28.093Z",
    "executionTime": 49,
    "rowCount": 3,
    "success": true,
    "userEmail": "ayush@flipkart.com",
    "orgId": "flipkart.com",
    "id": "history_1767375148093_c17q0k7lg"
  },
  {
    "connectionId": "conn_1767358132773_4q9xyimqd",
    "connectionName": "My Postgres Database",
    "query": "CREATE OR REPLACE PROCEDURE get_apple_count(OUT total INT)\r\nLANGUAGE plpgsql\r\nAS $$\r\nBEGIN\r\n    SELECT SUM(quantity) INTO total FROM apples;\r\nEND;\r\n$$",
    "executedAt": "2026-01-02T17:32:35.622Z",
    "executionTime": 92,
    "rowCount": 0,
    "success": true,
    "userEmail": "ayush@flipkart.com",
    "orgId": "flipkart.com",
    "id": "history_1767375155622_k7z5qwvh5"
  },
  {
    "connectionId": "conn_1767358132773_4q9xyimqd",
    "connectionName": "My Postgres Database",
    "query": "CALL get_apple_count(NULL)",
    "executedAt": "2026-01-02T17:32:39.311Z",
    "executionTime": 26,
    "rowCount": 0,
    "success": true,
    "userEmail": "ayush@flipkart.com",
    "orgId": "flipkart.com",
    "id": "history_1767375159311_rwflvzbde"
  },
  {
    "connectionId": "conn_1767358132773_4q9xyimqd",
    "connectionName": "My Postgres Database",
    "query": "CREATE TABLE CONTRACT_SUMMARY (\r\n    ID BIGINT IDENTITY(1,1) PRIMARY KEY,\r\n    CONTRACT_NUMBER VARCHAR(50) NOT NULL,\r\n    CONTRACT_TYPE VARCHAR(50),\r\n    START_DATE DATE,\r\n    END_DATE DATE,\r\n    MONTHLY_INSTALLMENT DECIMAL(15,2),\r\n    CURRENCY VARCHAR(10),\r\n    CONTRACT_STATUS VARCHAR(20),\r\n    CREATED_AT DATETIME DEFAULT GETDATE()\r\n)",
    "executedAt": "2026-01-02T17:44:39.015Z",
    "executionTime": 0,
    "rowCount": 0,
    "success": false,
    "error": "Query execution failed: syntax error at or near \"IDENTITY\"",
    "userEmail": "ayush@flipkart.com",
    "orgId": "flipkart.com",
    "id": "history_1767375879015_bhquqbe9s"
  },
  {
    "connectionId": "conn_1767358132773_4q9xyimqd",
    "connectionName": "My Postgres Database",
    "query": "CREATE TABLE CONTRACT_SUMMARY (\r\n    ID BIGINT IDENTITY(1,1) PRIMARY KEY,\r\n    CONTRACT_NUMBER VARCHAR(50) NOT NULL,\r\n    CONTRACT_TYPE VARCHAR(50),\r\n    START_DATE DATE,\r\n    END_DATE DATE,\r\n    MONTHLY_INSTALLMENT DECIMAL(15,2),\r\n    CURRENCY VARCHAR(10),\r\n    CONTRACT_STATUS VARCHAR(20),\r\n    CREATED_AT DATETIME DEFAULT GETDATE()\r\n)",
    "executedAt": "2026-01-02T17:44:41.735Z",
    "executionTime": 0,
    "rowCount": 0,
    "success": false,
    "error": "Query execution failed: syntax error at or near \"IDENTITY\"",
    "userEmail": "ayush@flipkart.com",
    "orgId": "flipkart.com",
    "id": "history_1767375881735_a9skiffvw"
  },
  {
    "connectionId": "conn_1767358132773_4q9xyimqd",
    "connectionName": "My Postgres Database",
    "query": "CREATE TABLE users (\r\n    id SERIAL PRIMARY KEY,\r\n    name VARCHAR(100),\r\n    email VARCHAR(150)\r\n)",
    "executedAt": "2026-01-02T17:45:13.176Z",
    "executionTime": 111,
    "rowCount": 0,
    "success": true,
    "userEmail": "ayush@flipkart.com",
    "orgId": "flipkart.com",
    "id": "history_1767375913176_ctxj2k0h0"
  },
  {
    "connectionId": "conn_1767358132773_4q9xyimqd",
    "connectionName": "My Postgres Database",
    "query": "DROP TABLE users",
    "executedAt": "2026-01-02T17:45:26.748Z",
    "executionTime": 22,
    "rowCount": 0,
    "success": true,
    "userEmail": "ayush@flipkart.com",
    "orgId": "flipkart.com",
    "id": "history_1767375926748_b4wohbo7v"
  },
  {
    "connectionId": "conn_1767358132773_4q9xyimqd",
    "connectionName": "My Postgres Database",
    "query": "DROP TABLE IF EXISTS users",
    "executedAt": "2026-01-02T17:46:36.505Z",
    "executionTime": 6,
    "rowCount": 0,
    "success": true,
    "userEmail": "ayush@flipkart.com",
    "orgId": "flipkart.com",
    "id": "history_1767375996505_vvvq8hv2b"
  },
  {
    "connectionId": "conn_1767358132773_4q9xyimqd",
    "connectionName": "My Postgres Database",
    "query": "CREATE TABLE users (\r\n    id SERIAL PRIMARY KEY,\r\n    name VARCHAR(100),\r\n    email VARCHAR(150)\r\n)",
    "executedAt": "2026-01-02T18:21:22.181Z",
    "executionTime": 66,
    "rowCount": 0,
    "success": true,
    "userEmail": "ayush@flipkart.com",
    "orgId": "flipkart.com",
    "id": "history_1767378082184_p02ckjj6l"
  },
  {
    "connectionId": "conn_1767358132773_4q9xyimqd",
    "connectionName": "My Postgres Database",
    "query": "-- Drop table",
    "executedAt": "2026-01-02T18:21:22.821Z",
    "executionTime": 3,
    "rowCount": 0,
    "success": true,
    "userEmail": "ayush@flipkart.com",
    "orgId": "flipkart.com",
    "id": "history_1767378082822_82ywww0tu"
  },
  {
    "connectionId": "conn_1767358132773_4q9xyimqd",
    "connectionName": "My Postgres Database",
    "query": "CREATE TABLE users (\r\n    id SERIAL PRIMARY KEY,\r\n    name VARCHAR(100),\r\n    email VARCHAR(150)\r\n)",
    "executedAt": "2026-01-02T18:21:25.161Z",
    "executionTime": 0,
    "rowCount": 0,
    "success": false,
    "error": "Query execution failed: relation \"users\" already exists",
    "userEmail": "ayush@flipkart.com",
    "orgId": "flipkart.com",
    "id": "history_1767378085161_t1qvkhwgj"
  },
  {
    "connectionId": "conn_1767358132773_4q9xyimqd",
    "connectionName": "My Postgres Database",
    "query": "SELECT * FROM public.users LIMIT 100",
    "executedAt": "2026-01-02T18:27:24.129Z",
    "executionTime": 4,
    "rowCount": 0,
    "success": true,
    "userEmail": "ayush@flipkart.com",
    "orgId": "flipkart.com",
    "id": "history_1767378444130_8vdmkec3k"
  },
  {
    "connectionId": "conn_1767358132773_4q9xyimqd",
    "connectionName": "My Postgres Database",
    "query": "INSERT INTO users (name, email)\r\nVALUES\r\n('Rahul', 'rahul@example.com'),\r\n('Ankit', 'ankit@example.com')",
    "executedAt": "2026-01-02T18:27:50.397Z",
    "executionTime": 23,
    "rowCount": 2,
    "success": true,
    "userEmail": "ayush@flipkart.com",
    "orgId": "flipkart.com",
    "id": "history_1767378470397_k02vv63rw"
  },
  {
    "connectionId": "conn_1767358132773_4q9xyimqd",
    "connectionName": "My Postgres Database",
    "query": "SELECT * FROM public.users LIMIT 100",
    "executedAt": "2026-01-02T18:27:54.036Z",
    "executionTime": 5,
    "rowCount": 2,
    "success": true,
    "userEmail": "ayush@flipkart.com",
    "orgId": "flipkart.com",
    "id": "history_1767378474036_swf4naxkl"
  },
  {
    "connectionId": "conn_1767358132773_4q9xyimqd",
    "connectionName": "My Postgres Database",
    "query": "DROP TABLE users",
    "executedAt": "2026-01-02T18:28:08.449Z",
    "executionTime": 49,
    "rowCount": 0,
    "success": true,
    "userEmail": "ayush@flipkart.com",
    "orgId": "flipkart.com",
    "id": "history_1767378488450_myb91m4hq"
  }
]