[
  {
    "id": "0ab971e0-687b-48e4-9a02-912f0e6c1557",
    "type": "postgres",
    "name": "My Postgres Database",
    "organizationId": "newgen.com",
    "containerName": "bosdb-newgen.com-postgres-1766887038880",
    "port": 5432,
    "username": "bosdb_4cfc8da9",
    "password": "9lUA908hFsicVta1/ReO",
    "database": "bosdb",
    "status": "running",
    "autoStart": true,
    "createdAt": "2025-12-28T01:57:18.881Z",
    "updatedAt": "2025-12-28T01:57:21.598Z",
    "containerId": "e318c86d4f32f759f89ef764394d38cebb3a5528f7b40ea2ffb6c44baa5bbcba"
  },
  {
    "id": "9086c4b2-3e64-4760-a94f-3c25be543085",
    "type": "postgres",
    "name": "My Postgres Database",
    "organizationId": "newgen.com",
    "containerName": "bosdb-newgen.com-postgres-1766887196896",
    "port": 5433,
    "username": "bosdb_244f75e6",
    "password": "2uChIVAmLfkmSJiYwHdl",
    "database": "bosdb",
    "status": "running",
    "autoStart": true,
    "createdAt": "2025-12-28T01:59:56.896Z",
    "updatedAt": "2025-12-28T01:59:59.447Z",
    "containerId": "16688e05f74f87b8156ad8310d5d2de558204386adc77b9d598b36f27ff3adb9"
  },
  {
    "id": "ecac8c29-29a5-4998-afe1-9598c8c40e15",
    "type": "postgres",
    "name": "My Postgres Database",
    "organizationId": "newgen.com",
    "containerName": "bosdb-newgen.com-postgres-1766887748098",
    "port": 5434,
    "username": "bosdb_e72b3777",
    "password": "ifHmEChOzefqhQX7A0qT",
    "database": "bosdb",
    "status": "running",
    "autoStart": true,
    "createdAt": "2025-12-28T02:09:08.098Z",
    "updatedAt": "2025-12-28T02:09:10.726Z",
    "containerId": "bbcbd14a89e509bc3f392b9ef8207dce6d9cec0a9a250bfe43f98b020dda2387"
  },
  {
    "id": "21c0a416-5634-4b89-837a-f038018da2e0",
    "type": "postgres",
    "name": "My Postgres Database",
    "organizationId": "newgen.com",
    "containerName": "bosdb-newgen.com-postgres-1766888896164",
    "port": 5435,
    "username": "bosdb_3385ebf8",
    "password": "945JShz6m+2xI+0qMa0e",
    "database": "bosdb",
    "status": "running",
    "autoStart": true,
    "createdAt": "2025-12-28T02:28:16.165Z",
    "updatedAt": "2025-12-28T02:28:19.376Z",
    "containerId": "b9d4da8c10afc3730ef7ec98fa8f0112d5c88835337cc64693aa2c4d5f4e86da"
  },
  {
    "id": "647066a6-231d-460b-a950-f54d0db33831",
    "type": "mongodb",
    "name": "My Mongodb Database",
    "organizationId": "newgen.com",
    "containerName": "bosdb-newgen.com-mongodb-1766888904551",
    "port": 27017,
    "username": "bosdb_d184b468",
    "password": "n08eJSrpuzkcfgVT5z04",
    "database": "bosdb",
    "status": "running",
    "autoStart": true,
    "createdAt": "2025-12-28T02:28:24.551Z",
    "updatedAt": "2025-12-28T02:29:34.791Z",
    "containerId": "1f7a6d1024857064806be141b22d17b0f5262d570f8fad83e80b1a388a8cd815"
  },
  {
    "id": "ba50cfd8-94de-482f-9dea-9983e24df555",
    "type": "postgres",
    "name": "My Postgres Database",
    "organizationId": "newgen.com",
    "containerName": "bosdb-newgen.com-postgres-1766889146211",
    "port": 5436,
    "username": "bosdb_132371e7",
    "password": "FKHtpqQ636Ogmct3sKBq",
    "database": "bosdb",
    "status": "running",
    "autoStart": true,
    "createdAt": "2025-12-28T02:32:26.212Z",
    "updatedAt": "2025-12-28T02:32:31.566Z",
    "containerId": "d4551abae12c9ebfc9352b199b130a350929d93fa2d9471c0049e94eae971076"
  },
  {
    "id": "77c21da7-b01e-4a60-a7a8-81e20e87fd5a",
    "type": "postgres",
    "name": "My Postgres Database",
    "organizationId": "newgen.com",
    "containerName": "bosdb-newgen.com-postgres-1766889154866",
    "port": 5437,
    "username": "bosdb_4ace717b",
    "password": "cJYtIuZZQaAWdxMXKDF3",
    "database": "bosdb",
    "status": "running",
    "autoStart": true,
    "createdAt": "2025-12-28T02:32:34.866Z",
    "updatedAt": "2025-12-28T02:32:37.570Z",
    "containerId": "64b3742f9d6bb0e96f85b4c227f1804789df2d5ccec455482d1e2b56c16da784"
  },
  {
    "id": "9a30b3e2-ca2d-4bb7-ac33-af7c8a923950",
    "type": "postgres",
    "name": "My Postgres Database",
    "organizationId": "newgen.com",
    "containerName": "bosdb-newgen.com-postgres-1766889158917",
    "port": 5438,
    "username": "bosdb_9966d487",
    "password": "lIAAwHsKwGiNLKAAuxCA",
    "database": "bosdb",
    "status": "running",
    "autoStart": true,
    "createdAt": "2025-12-28T02:32:38.917Z",
    "updatedAt": "2025-12-28T02:32:41.909Z",
    "containerId": "bcccd07a5b66cd0b7c53511579d647637b2e1022edb5bc261198c1bab918e11c"
  },
  {
    "id": "f7fd5f77-422a-4c29-b65c-3e4ef38a84f7",
    "type": "mongodb",
    "name": "My Mongodb Database",
    "organizationId": "newgen.com",
    "containerName": "bosdb-newgen.com-mongodb-1766889165756",
    "port": 27018,
    "username": "bosdb_4c641eaa",
    "password": "8Ot9NjQhMCTogxWB2ETV",
    "database": "bosdb",
    "status": "running",
    "autoStart": true,
    "createdAt": "2025-12-28T02:32:45.756Z",
    "updatedAt": "2025-12-28T02:32:54.436Z",
    "containerId": "963a440cf6eedc1b7c158a4ef96d6de141ce79ee72c287b7dc092148d4b16ba5"
  },
  {
    "id": "d823b0e3-5300-4e8d-8e73-a11e09910795",
    "type": "postgres",
    "name": "My Postgres Database",
    "organizationId": "newgen.com",
    "containerName": "bosdb-newgen.com-postgres-1766889295735",
    "port": 5439,
    "username": "bosdb_1ec01e97",
    "password": "5HcWqA12MfqqVwz2vREN",
    "database": "bosdb",
    "status": "running",
    "autoStart": true,
    "createdAt": "2025-12-28T02:34:55.736Z",
    "updatedAt": "2025-12-28T02:34:58.772Z",
    "containerId": "b5a5d947dfe6ee957e80366f5aa38477b18d8a2718893fc5e7a9f49c2e8afc8e"
  },
  {
    "id": "cae210ec-da78-45b8-985f-490dbeec09b7",
    "type": "postgres",
    "name": "My Postgres Database",
    "organizationId": "newgen.com",
    "containerName": "bosdb-newgen.com-postgres-1766889497386",
    "port": 5440,
    "username": "bosdb_5d803652",
    "password": "E+J0TdjZ8oWLZUhVp0Nb",
    "database": "bosdb",
    "status": "running",
    "autoStart": true,
    "createdAt": "2025-12-28T02:38:17.387Z",
    "updatedAt": "2025-12-28T02:38:24.742Z",
    "containerId": "40c72dad57f4ff2ce6b4b2c8359ad08a2f7cf28751150eba1f5a21457dc9571d"
  },
  {
    "id": "7cba9c98-67d2-4cdf-820c-1bd21413d9c5",
    "type": "postgres",
    "name": "My Postgres Database",
    "organizationId": "newgen.com",
    "containerName": "bosdb-newgen.com-postgres-1766889671327",
    "port": 5441,
    "username": "bosdb_8b6f5adf",
    "password": "255k91PxdekUGTvWP7Ce",
    "database": "bosdb",
    "status": "running",
    "autoStart": true,
    "createdAt": "2025-12-28T02:41:11.328Z",
    "updatedAt": "2025-12-28T02:41:16.441Z",
    "containerId": "e2a948dc4d8af7b40089b69509590754816c1a0d0b269a67059294e88dcb0aa8"
  },
  {
    "id": "2e668ab3-4520-496c-9903-c1fbf472722c",
    "type": "postgres",
    "name": "My Postgres Database",
    "organizationId": "newgen.com",
    "containerName": "bosdb-newgen.com-postgres-1766890185995",
    "port": 5442,
    "username": "bosdb_95a6afcb",
    "password": "XPydJQDNcUwmeWfaEdvz",
    "database": "bosdb",
    "status": "running",
    "autoStart": true,
    "createdAt": "2025-12-28T02:49:45.995Z",
    "updatedAt": "2025-12-28T02:49:50.544Z",
    "containerId": "d6101a22ba71c1c44a3d5fadf95dee37fa7dec83778b955c1791c670496fb74e"
  },
  {
    "id": "ba7b8a0c-eaac-47b7-9a47-90d14ac3b5a1",
    "type": "postgres",
    "name": "My Postgres Database",
    "organizationId": "newgen.com",
    "containerName": "bosdb-newgen.com-postgres-1766890310622",
    "port": 5443,
    "username": "bosdb_6533f58a",
    "password": "eCQg3AJowV978DRB6R8F",
    "database": "bosdb",
    "status": "running",
    "autoStart": true,
    "createdAt": "2025-12-28T02:51:50.622Z",
    "updatedAt": "2025-12-28T02:51:54.819Z",
    "containerId": "f2f0d08a5442221b1fde117eee2e47ea37bb5f5431877cd889c79e0b4c134a7b"
  },
  {
    "id": "0fe5750f-1f7f-4606-928f-8b5c0af692c3",
    "type": "postgres",
    "name": "My Postgres Database",
    "organizationId": "newgen.com",
    "containerName": "bosdb-newgen.com-postgres-1766890567724",
    "port": 5444,
    "username": "bosdb_223a0ddf",
    "password": "Kg5xejxMIq+OcXFGB+Wb",
    "database": "bosdb",
    "status": "running",
    "autoStart": true,
    "createdAt": "2025-12-28T02:56:07.725Z",
    "updatedAt": "2025-12-28T02:56:12.138Z",
    "containerId": "81d3c4fa7e2ae4a24fc8a7d63633d27f189f1eeff28cee4bceec48d3dbb5b8a5"
  },
  {
    "id": "8e74034b-a4ab-47dc-a4dc-a2b623d7883a",
    "type": "postgres",
    "name": "My Postgres Database",
    "organizationId": "newgen.com",
    "containerName": "bosdb-newgen.com-postgres-1766890672028",
    "port": 5445,
    "username": "bosdb_b387485c",
    "password": "9YxVaRc2eekxIwmMFE1R",
    "database": "bosdb",
    "status": "running",
    "autoStart": true,
    "createdAt": "2025-12-28T02:57:52.028Z",
    "updatedAt": "2025-12-28T02:57:54.952Z",
    "containerId": "bdeed7f7d7f03abb26ed0b2b202f5a96cc1be6e70648e02f70eae544527c5d75"
  },
  {
    "id": "893f13c2-bb3a-4d71-9f8d-ed6f63632d7e",
    "type": "machbase",
    "name": "My Machbase Database",
    "organizationId": "newgen.com",
    "containerName": "bosdb-newgen.com-machbase-1766891876365",
    "port": 5656,
    "username": "bosdb_34af6f7a",
    "password": "QOqvmSCC79UoprXKWKii",
    "database": "bosdb",
    "status": "running",
    "autoStart": true,
    "createdAt": "2025-12-28T03:17:56.370Z",
    "updatedAt": "2025-12-28T03:19:02.748Z",
    "containerId": "b9362efa2223f59fec7b0918b711ec3fda36632233664b045bb8da520b6b9c15"
  },
  {
    "id": "5a610883-f4e3-4a3d-9682-ea05281bb578",
    "type": "postgres",
    "name": "My Postgres Database",
    "organizationId": "newgen.com",
    "containerName": "bosdb-newgen.com-postgres-1766898422168",
    "port": 5446,
    "username": "bosdb_c4f76778",
    "password": "wiDCK7DRPzwvx2bkG7jG",
    "database": "bosdb",
    "status": "running",
    "autoStart": true,
    "createdAt": "2025-12-28T05:07:02.169Z",
    "updatedAt": "2025-12-28T05:07:08.954Z",
    "containerId": "b0f874c7641a9b546e78260cb8f8bbde61482d84d6ccdf1dd74fb7f458f89945"
  },
  {
    "id": "67c7d66e-6415-4f4c-b6de-c290861c0656",
    "type": "postgres",
    "name": "My Postgres Database",
    "organizationId": "newgen.com",
    "containerName": "bosdb-newgen.com-postgres-1766898563998",
    "port": 5447,
    "username": "bosdb_6d0d0d69",
    "password": "5xgpbGpYtrQ52VOkIPtW",
    "database": "bosdb",
    "status": "running",
    "autoStart": true,
    "createdAt": "2025-12-28T05:09:23.999Z",
    "updatedAt": "2025-12-28T05:09:34.657Z",
    "containerId": "ea19f945aab0ac8614e2ea7166c4e79681a3c7e601dd03814657092e2eb858aa"
  },
  {
    "id": "1d5b553c-fbbd-48db-ae72-876317515735",
    "type": "mysql",
    "name": "My Mysql Database",
    "organizationId": "newgen.com",
    "containerName": "bosdb-newgen.com-mysql-1766898483700",
    "port": 3306,
    "username": "bosdb_a5eba6cf",
    "password": "XOjPHb1UVFgiA2GELj1D",
    "database": "bosdb",
    "status": "running",
    "autoStart": true,
    "createdAt": "2025-12-28T05:08:03.700Z",
    "updatedAt": "2025-12-28T05:09:57.617Z",
    "containerId": "6225d9d2b8c39c332e317407340165f877ee4a7753151b1c385d9b912127c9b2"
  },
  {
    "id": "5c6edc59-799d-417a-8c5a-80cfe526fdf2",
    "type": "postgres",
    "name": "My Postgres Database",
    "organizationId": "newgen.com",
    "containerName": "bosdb-newgen.com-postgres-1766898736106",
    "port": 5448,
    "username": "bosdb_dba33e21",
    "password": "6Al8rUdW+ri2KfaEVTYt",
    "database": "bosdb",
    "status": "running",
    "autoStart": true,
    "createdAt": "2025-12-28T05:12:16.107Z",
    "updatedAt": "2025-12-28T05:12:24.205Z",
    "containerId": "b0e36d7995b226ce00de4005414128dd75fa3829e1d521bac4e07e433800cd85"
  }
]